dataverk_airflow/__init__.py
dataverk_airflow/bucket_read.py
dataverk_airflow/git_clone.py
dataverk_airflow/kubernetes_operator.py
dataverk_airflow/notebook_operator.py
dataverk_airflow/notifications.py
dataverk_airflow/python_operator.py
dataverk_airflow/quarto_operator.py
dataverk_airflow-1.8.2.dist-info/METADATA
dataverk_airflow-1.8.2.dist-info/WHEEL
dataverk_airflow-1.8.2.dist-info/licenses/LICENSE
dataverk_airflow-1.8.2.dist-info/RECORD
