Metadata-Version: 2.4
Name: dataverk-airflow
Version: 1.8.2
Summary: 
License-File: LICENSE
Author: NAV
Requires-Python: >=3.9,<3.13
Classifier: Development Status :: 5 - Production/Stable
Classifier: Framework :: Apache Airflow
Classifier: Framework :: Apache Airflow :: Provider
Classifier: Programming Language :: Python :: 3
Classifier: Programming Language :: Python :: 3.9
Classifier: Programming Language :: Python :: 3.10
Classifier: Programming Language :: Python :: 3.11
Classifier: Programming Language :: Python :: 3.12
Requires-Dist: apache-airflow (==2.11.0)
Requires-Dist: apache-airflow-providers-cncf-kubernetes (>=8.3.3,<9.0.0)
Requires-Dist: apache-airflow-providers-slack (>=8.7.1,<9.0.0)
Requires-Dist: exceptiongroup (>=1.2.2,<2.0.0)
Requires-Dist: knatch (>=1.1.0,<2.0.0)
Requires-Dist: pathlib (>=1.0.1,<2.0.0)
Project-URL: Repository, https://github.com/navikt/dataverk-airflow
